aimmocore/__init__.py
aimmocore/config.py
aimmocore/curation.py
aimmocore/main.py
aimmocore/core/__init__.py
aimmocore/core/database.py
aimmocore/core/event.py
aimmocore/core/images.py
aimmocore/core/services.py
aimmocore/core/storages.py
aimmocore/core/utils.py
aimmocore/core/zoo.py
aimmocore/core/__pycache__/__init__.cpython-38.pyc
aimmocore/core/__pycache__/database.cpython-38.pyc
aimmocore/core/__pycache__/event.cpython-38.pyc
aimmocore/core/__pycache__/images.cpython-38.pyc
aimmocore/core/__pycache__/services.cpython-38.pyc
aimmocore/core/__pycache__/storages.cpython-38.pyc
aimmocore/core/__pycache__/utils.cpython-38.pyc
aimmocore/core/__pycache__/zoo.cpython-38.pyc
aimmocore/server/__init__.py
aimmocore/server/app.py
aimmocore/server/__pycache__/__init__.cpython-38.pyc
aimmocore/server/__pycache__/app.cpython-38.pyc
aimmocore/server/__pycache__/configs.cpython-38.pyc
aimmocore/server/routers/__init__.py
aimmocore/server/routers/datasets.py
aimmocore/server/routers/systems.py
aimmocore/server/routers/__pycache__/__init__.cpython-38.pyc
aimmocore/server/routers/__pycache__/datasets.cpython-38.pyc
aimmocore/server/routers/__pycache__/files.cpython-38.pyc
aimmocore/server/routers/__pycache__/systems.cpython-38.pyc
aimmocore/server/schemas/__init__.py
aimmocore/server/schemas/base.py
aimmocore/server/schemas/datasets.py
aimmocore/server/schemas/__pycache__/__init__.cpython-38.pyc
aimmocore/server/schemas/__pycache__/base.cpython-38.pyc
aimmocore/server/schemas/__pycache__/datasets.cpython-38.pyc
aimmocore/server/services/__init__.py
aimmocore/server/services/datasets.py
aimmocore/server/services/__pycache__/__init__.cpython-38.pyc
aimmocore/server/services/__pycache__/datasets.cpython-38.pyc
aimmocore/server/services/__pycache__/dummies.cpython-38.pyc
aimmocore/server/services/__pycache__/files.cpython-38.pyc
aimmocore/server/static/BVHLoader-ZWWK3QWK.js
aimmocore/server/static/CSS2DRenderer-RJ62ZDXC.js
aimmocore/server/static/CSS3DRenderer-3QF5ZVNS.js
aimmocore-0.1.15.dist-info/LICENSE
aimmocore-0.1.15.dist-info/METADATA
aimmocore-0.1.15.dist-info/WHEEL
aimmocore-0.1.15.dist-info/top_level.txt
aimmocore-0.1.15.dist-info/RECORD
