Metadata-Version: 2.1
Name: aimmocore
Version: 0.1.15
Summary: The sdk for aimmocore curation service
Author-email: Aimmo <aimmocore-dev@aimmo.co.kr>
License: AIMMO, apache 2.0
Classifier: Development Status :: 4 - Beta
Classifier: Programming Language :: Python :: 3.8
Requires-Python: >=3.8
License-File: LICENSE
Requires-Dist: uvicorn
Requires-Dist: hypercorn
Requires-Dist: starlette>=0.38.0
Requires-Dist: loguru
Requires-Dist: pydantic
Requires-Dist: pyhumps
Requires-Dist: azure-storage-blob
Requires-Dist: motor
Requires-Dist: aimmocore-db
Requires-Dist: nest-asyncio
Requires-Dist: pillow
Requires-Dist: IPython
Requires-Dist: aiohttp
Requires-Dist: aiofiles
Requires-Dist: tqdm
Requires-Dist: psutil
Requires-Dist: apscheduler
